README
setup.py
dm/__init__.py
dm.pdb.egg-info/PKG-INFO
dm.pdb.egg-info/SOURCES.txt
dm.pdb.egg-info/dependency_links.txt
dm.pdb.egg-info/namespace_packages.txt
dm.pdb.egg-info/requires.txt
dm.pdb.egg-info/top_level.txt
dm.pdb.egg-info/zip-safe
dm/pdb/LICENSE.txt
dm/pdb/README.txt
dm/pdb/VERSION.txt
dm/pdb/__init__.py
dm/pdb/dmpdb.py
dm/pdb/proxy.py
dm/pdb/zpdb.py