Metadata-Version: 1.1
Name: dm.pdb
Version: 1.3
Summary: Slightly extended and sanitized Python debugger -- Debugger with Zope support
Home-page: UNKNOWN
Author: Dieter Maurer
Author-email: dieter@handshake.de
License: BSD (see "dm/pdb/LICENSE.txt", for details)
Keywords: debugger pdb Zope
Platform: UNKNOWN
Classifier: Development Status :: 5 - Production/Stable
Classifier: Intended Audience :: Developers
Classifier: License :: OSI Approved :: BSD License
Classifier: Operating System :: OS Independent
Classifier: Programming Language :: Python
Classifier: Programming Language :: Python :: 2.7
Classifier: Programming Language :: Python :: 3
Classifier: Topic :: Software Development
